MANIFEST.in
requirements.txt
setup.py
concord/__init__.py
concord/computation.py
concord/internal/__init__.py
concord/internal/thrift/BoltManagerService.py
concord/internal/thrift/BoltMetricsService.py
concord/internal/thrift/BoltPipeService.py
concord/internal/thrift/BoltProxyService.py
concord/internal/thrift/BoltSchedulerService.py
concord/internal/thrift/ComputationService.py
concord/internal/thrift/MutableEphemeralStateService.py
concord/internal/thrift/__init__.py
concord/internal/thrift/constants.py
concord/internal/thrift/ttypes.py
concord_py.egg-info/PKG-INFO
concord_py.egg-info/SOURCES.txt
concord_py.egg-info/dependency_links.txt
concord_py.egg-info/requires.txt
concord_py.egg-info/top_level.txt