Metadata-Version: 1.0
Name: concord-py
Version: 0.3.5
Summary: concord.io python client library
Home-page: http://concord.io
Author: concord systems
Author-email: hi@concord.io
License: UNKNOWN
Platform: UNKNOWN
